ai_shell/__init__.py
ai_shell/cli.py
ai_shell/prompt.py
ai_shell/commands/__init__.py
ai_shell/commands/config.py
ai_shell/commands/update.py
ai_shell/helpers/__init__.py
ai_shell/helpers/ai_process.py
ai_shell/helpers/command_history.py
ai_shell/helpers/completion.py
ai_shell/helpers/config.py
ai_shell/helpers/constants.py
ai_shell/helpers/editor.py
ai_shell/helpers/error.py
ai_shell/helpers/os_detect.py
ai_shell/helpers/shell_history.py
ai_shell/helpers/styling.py
py_ai_shell-0.1.3.dist-info/LICENSE
py_ai_shell-0.1.3.dist-info/METADATA
py_ai_shell-0.1.3.dist-info/WHEEL
py_ai_shell-0.1.3.dist-info/entry_points.txt
py_ai_shell-0.1.3.dist-info/top_level.txt
py_ai_shell-0.1.3.dist-info/RECORD
